{
    "id": "3",
    "type": "reading",
    "title": "Read Other Things",
    "stats": [{
        "period_id": "1",
        "total_exercises_count": 100,
        "complete_exercises_count": 100,
        "correct_exercises_count": 71,
        "total_tasks_count": 10,
        "complete_tasks_count": 10,
        "partially_complete_tasks_count": 0,
        "current_pages": [],
        "spaced_pages": [{
            "id": "0",
            "chapter_section": [4, 2],
            "title": "",
            "student_count": 10,
            "correct_count": 120,
            "incorrect_count": 50
        }]
    },{
        "period_id": "2",
        "total_exercises_count": 100,
        "complete_exercises_count": 100,
        "correct_exercises_count": 71,
        "total_tasks_count": 10,
        "complete_tasks_count": 10,
        "partially_complete_tasks_count": 0,
        "current_pages": [],
        "spaced_pages": [{
            "id": "0",
            "chapter_section": [4, 2],
            "title": "",
            "student_count": 10,
            "correct_count": 120,
            "incorrect_count": 50
        }]
    },{
        "period_id": "3",
        "total_exercises_count": 100,
        "complete_exercises_count": 100,
        "correct_exercises_count": 71,
        "total_tasks_count": 10,
        "complete_tasks_count": 10,
        "partially_complete_tasks_count": 0,
        "current_pages": [],
        "spaced_pages": [{
            "id": "0",
            "chapter_section": [4, 2],
            "title": "",
            "student_count": 10,
            "correct_count": 120,
            "incorrect_count": 50
        }]
    },{
        "period_id": "4",
        "total_exercises_count": 100,
        "complete_exercises_count": 100,
        "correct_exercises_count": 71,
        "total_tasks_count": 10,
        "complete_tasks_count": 10,
        "partially_complete_tasks_count": 0,
        "current_pages": [],
        "spaced_pages": [{
            "id": "0",
            "chapter_section": [4, 2],
            "title": "",
            "student_count": 10,
            "correct_count": 120,
            "incorrect_count": 50
        }]
    },{
        "period_id": "5",
        "total_exercises_count": 100,
        "complete_exercises_count": 100,
        "correct_exercises_count": 71,
        "total_tasks_count": 10,
        "complete_tasks_count": 10,
        "partially_complete_tasks_count": 0,
        "current_pages": [],
        "spaced_pages": [{
            "id": "0",
            "chapter_section": [4, 2],
            "title": "",
            "student_count": 10,
            "correct_count": 120,
            "incorrect_count": 50
        }]
    },{
        "period_id": "6",
        "total_exercises_count": 100,
        "complete_exercises_count": 100,
        "correct_exercises_count": 71,
        "total_tasks_count": 10,
        "complete_tasks_count": 10,
        "partially_complete_tasks_count": 0,
        "current_pages": [],
        "spaced_pages": [{
            "id": "0",
            "chapter_section": [4, 2],
            "title": "",
            "student_count": 10,
            "correct_count": 120,
            "incorrect_count": 50
        }]
    },{
        "period_id": "7",
        "total_exercises_count": 100,
        "complete_exercises_count": 100,
        "correct_exercises_count": 71,
        "total_tasks_count": 10,
        "complete_tasks_count": 10,
        "partially_complete_tasks_count": 0,
        "current_pages": [],
        "spaced_pages": [{
            "id": "0",
            "chapter_section": [4, 2],
            "title": "",
            "student_count": 10,
            "correct_count": 120,
            "incorrect_count": 50
        }]
    }]
}
